{
  "forge_marker": 1,
  "defaults": {
    "textures": {
      "up": "techreimagined:blocks/machines/digital/BuilderTopOn",
      "down": "techreimagined:blocks/machines/digital/BuilderBottom",
      "north": "techreimagined:blocks/machines/digital/BuilderFront",
      "east": "techreimagined:blocks/machines/digital/BuilderLeftOn",
      "west": "techreimagined:blocks/machines/digital/BuilderRightOn",
      "south": "techreimagined:blocks/machines/digital/BuilderBackOn",
      "particle": "techreimagined:blocks/machines/digital/BuilderFront"
    },
    "model": "minecraft:cube",
    "transform": "forge:default-block"
  },
  "variants": {
    "inventory": [
      {}
    ],
    "facing": {
      "west": {
        "y": -90
      },
      "east": {
        "y": 90
      },
      "north": {
      },
      "south": {
        "y": 180
      }
    }
  }
}